{
  "id": "ginasta",
  "nome": "Ginasta",
  "descricao": "pessoas que passaram a vida treinando seus corpos. São atléticos, rápidos e flexíveis. Se envolveram com aspectos místicos em alguma de suas competições ou treinos. Bônus em Atletismo e Acrobacia +2.",
  "bonus": {
      "pericias": {
        "atletismo": 2,
        "acrobacia": 2
      },
    "equipamento": "Roupas de treino, equipamentos de ginástica, moedas"
  },
  "caracteristicas": ["Agilidade", "Flexibilidade", "Disciplina física"]
}
